{
    "docs/introduction.md": "Introduction",
    "docs/installation.md": "Installation",
    "docs/getting-started.md": "Getting Started",
    "docs/fullstacked-vs.md": "Compared to Other Tools",
    "docs/guides/files.md": "Files Structure",
    "docs/guides/typescript.md": "TypeScript",
    "docs/guides/sass.md": "Sass/SCSS",
    "docs/guides/packages.md": "Packages",
    "docs/guides/git.md": "git",
    "docs/guides/open-in-fullstacked.md": "Open in FullStacked",
    "docs/guides/import-export.md": "Import & Export",
    "docs/guides/debugging.md": "Debugging",
    "docs/references/fs.md": "Files System (fs)",
    "docs/references/fetch.md": "Fetch (core_fetch)",
    "docs/privacy-policy.md": "Privacy Policy",
    "docs/references/platform.md": "Platform (platform)",
    "docs/references/archive.md": "Archive",
    "docs/references/zip.md": "ZIP (archive)",
    "docs/guides/terminal.md": "Using the terminal",
    "docs/guides/user-mode.md": "User Mode",
    "docs/guides/build.md": "Build from source",
    "docs/guides/prompt.md": "Prompt",
    "docs/guides/ai-agent.md": "AI Agent",
    "docs/license.md": "License",
    "docs/guides/kiosk.md": "Kiosk",
    "docs/references/ai.md": "AI (ai)",
    "docs/references/connect.md": "Connect (connect)",
    "docs/guides/vscode.md": "VS Code Setup"
}